{"_type": "News", "readLink": "https://api.bing.microsoft.com/api/v7/news/search?q=%22Amber+Lea+Dewitt%22%2binbody%3apolice", "queryContext": {"originalQuery": "\"Amber Lea Dewitt\"+inbody:police", "adultIntent": false}, "totalEstimatedMatches": 1, "sort": [{"name": "Best match", "id": "relevance", "isSelected": true, "url": "https://api.bing.microsoft.com/api/v7/news/search?q=%22Amber+Lea+Dewitt%22%2binbody%3apolice"}, {"name": "Most recent", "id": "date", "isSelected": false, "url": "https://api.bing.microsoft.com/api/v7/news/search?q=%22Amber+Lea+Dewitt%22%2binbody%3apolice&sortby=date"}], "value": [{"name": "Police: Woman killed had BB gun that looked 9mm handgun", "url": "https://www.ksl.com/article/46662030/police-woman-killed-had-bb-gun-that-looked-9mm-handgun", "description": "The Meridian Police Department on Thursday released ... officer-involved shooting on Sunday that killed 33-year-old Amber Lea Dewitt of Caldwell. Police also released photos of the light-blue ...", "provider": [{"_type": "Organization", "name": "KSL"}], "datePublished": "2019-10-25T17:26:00.0000000Z"}]}