{"_type": "News", "readLink": "https://api.bing.microsoft.com/api/v7/news/search?q=%22Alexander+Myers%22%2binbody%3apolice", "queryContext": {"originalQuery": "\"Alexander Myers\"+inbody:police", "adultIntent": false}, "totalEstimatedMatches": 1, "sort": [{"name": "Best match", "id": "relevance", "isSelected": true, "url": "https://api.bing.microsoft.com/api/v7/news/search?q=%22Alexander+Myers%22%2binbody%3apolice"}, {"name": "Most recent", "id": "date", "isSelected": false, "url": "https://api.bing.microsoft.com/api/v7/news/search?q=%22Alexander+Myers%22%2binbody%3apolice&sortby=date"}], "value": [{"name": "DUI driver who crashed into Palm Bay diner claims brakes didn\u2019t work, police say", "url": "https://www.clickorlando.com/news/local/2021/05/24/dui-driver-who-crashed-into-palm-bay-diner-claims-brakes-didnt-work-police-say/", "image": {"thumbnail": {"contentUrl": "https://www.bing.com/th?id=OVFT.9w5ZP_Yuf5lykURueqtbxC&pid=News", "width": 700, "height": 393}}, "description": "A man who crashed into a diner while driving under the influence blamed malfunctioning brakes for the crash, according to the Palm Bay Police Department.", "about": [{"readLink": "https://api.bing.microsoft.com/api/v7/entities/0a6e1490-a983-4f12-adc0-f7a8a7ca66c1", "name": "Palm Bay"}], "provider": [{"_type": "Organization", "name": "Click Orlando"}], "datePublished": "2021-05-24T20:12:00.0000000Z", "category": "US"}]}