{"_type": "News", "readLink": "https://api.bing.microsoft.com/api/v7/news/search?q=%22German+Mata%22%2binbody%3apolice", "queryContext": {"originalQuery": "\"German Mata\"+inbody:police", "adultIntent": false}, "totalEstimatedMatches": 1, "sort": [{"name": "Best match", "id": "relevance", "isSelected": true, "url": "https://api.bing.microsoft.com/api/v7/news/search?q=%22German+Mata%22%2binbody%3apolice"}, {"name": "Most recent", "id": "date", "isSelected": false, "url": "https://api.bing.microsoft.com/api/v7/news/search?q=%22German+Mata%22%2binbody%3apolice&sortby=date"}], "value": [{"name": "Neil Mackay: The strange saga of Scotland, spies and Special Forces", "url": "https://www.heraldscotland.com/news/18423338.neil-mackay-strange-saga-scotland-spies-special-forces/", "description": "He started out as a colonial policeman, serving in the Indian Imperial Police from 1900 to 1936 ... Vera Eriksen \u2013 the German Mata Hari \u2013 was snared at a Buckie railway station.", "about": [{"readLink": "https://api.bing.microsoft.com/api/v7/entities/a0377d96-1a18-f843-65ad-adcbc4acdc69", "name": "Scotland"}, {"readLink": "https://api.bing.microsoft.com/api/v7/entities/9cf3c30f-4524-55e3-bfd8-a946f0977c76", "name": "The Herald"}, {"readLink": "https://api.bing.microsoft.com/api/v7/entities/7d78f88b-9a31-f436-8975-af855821d0e8", "name": "Emily the Strange"}], "provider": [{"_type": "Organization", "name": "heraldscotland.com"}], "datePublished": "2020-05-03T09:34:00.0000000Z"}]}