{"_type": "News", "readLink": "https://api.bing.microsoft.com/api/v7/news/search?q=%22Edward+%22Eddie%22+Russell+Jr.%22%2binbody%3apolice", "queryContext": {"originalQuery": "\"Edward \"Eddie\" Russell Jr.\"+inbody:police", "adultIntent": false}, "totalEstimatedMatches": 1, "sort": [{"name": "Best match", "id": "relevance", "isSelected": true, "url": "https://api.bing.microsoft.com/api/v7/news/search?q=%22Edward+%22Eddie%22+Russell+Jr.%22%2binbody%3apolice"}, {"name": "Most recent", "id": "date", "isSelected": false, "url": "https://api.bing.microsoft.com/api/v7/news/search?q=%22Edward+%22Eddie%22+Russell+Jr.%22%2binbody%3apolice&sortby=date"}], "value": [{"name": "Experience key to beating Devin Haney, says former champ Jorge Linares", "url": "https://ca.news.yahoo.com/experience-key-to-beating-devin-haney-says-former-champ-jorge-linares-165813389.html", "description": "Promoter Eddie Hearn wanted a tough test for Haney and Linares insists ... He\u2019s got lightning quick hands, maybe faster than anyone this side of Gary Russell Jr., and yet he pooh-poohed that. The important thing to time is timing. It\u2019s setting up ...", "about": [{"readLink": "https://api.bing.microsoft.com/api/v7/entities/a2498844-5006-5813-6211-679153165758", "name": "Jorge Linares"}], "provider": [{"_type": "Organization", "name": "Yahoo News"}], "datePublished": "2021-05-27T17:58:00.0000000Z"}]}