{"_type": "News", "readLink": "https://api.bing.microsoft.com/api/v7/news/search?q=%22John+Deming+Jr%22%2binbody%3apolice", "queryContext": {"originalQuery": "\"John Deming Jr\"+inbody:police", "adultIntent": false}, "totalEstimatedMatches": 1, "sort": [{"name": "Best match", "id": "relevance", "isSelected": true, "url": "https://api.bing.microsoft.com/api/v7/news/search?q=%22John+Deming+Jr%22%2binbody%3apolice"}, {"name": "Most recent", "id": "date", "isSelected": false, "url": "https://api.bing.microsoft.com/api/v7/news/search?q=%22John+Deming+Jr%22%2binbody%3apolice&sortby=date"}], "value": [{"name": "John Deming Jr.", "url": "https://sanfrancisco.cbslocal.com/tag/john-deming-jr/", "description": "Pleasanton Cop Who Fatally Shot Teenager Cleared Of Criminal ChargesA Pleasanton police officer who shot and killed the son of an Oakdale reserve police officer last summer during a bizarre ...", "provider": [{"_type": "Organization", "name": "CBS SF BayArea"}], "datePublished": "2015-07-16T20:05:00.0000000Z"}]}