{"_type": "News", "readLink": "https://api.bing.microsoft.com/api/v7/news/search?q=%22Joseph+Garcia%22%2binanchor%3apolice", "queryContext": {"originalQuery": "\"Joseph Garcia\"+inanchor:police", "adultIntent": false}, "totalEstimatedMatches": 2, "sort": [{"name": "Best match", "id": "relevance", "isSelected": true, "url": "https://api.bing.microsoft.com/api/v7/news/search?q=%22Joseph+Garcia%22%2binanchor%3apolice"}, {"name": "Most recent", "id": "date", "isSelected": false, "url": "https://api.bing.microsoft.com/api/v7/news/search?q=%22Joseph+Garcia%22%2binanchor%3apolice&sortby=date"}], "value": [{"name": "Driver Fatally Hits San Jose Siblings During Car Chase With Police", "url": "https://news.yahoo.com/driver-fatally-hits-san-jose-160238160.html", "description": "What happened: The fatal crash happened around 10 p.m. on April 26 when officers attempted to pull over the suspect, Roberto Joseph Garcia of Morgan Hill, Calif., at Lawrence Expressway, according to KTVU. The Santa Clara County Medical Examiner-Coroner ...", "about": [{"readLink": "https://api.bing.microsoft.com/api/v7/entities/9e29752d-7c58-41ab-9226-27afc9a96968", "name": "San Jose"}, {"readLink": "https://api.bing.microsoft.com/api/v7/entities/9e96aac3-fa49-d8b9-9310-7bfeff2cce02", "name": "Police"}, {"readLink": "https://api.bing.microsoft.com/api/v7/entities/761ca11b-5cb2-cd60-7b34-29c22b95c47b", "name": "Sibling"}], "provider": [{"_type": "Organization", "name": "Yahoo News"}], "datePublished": "2021-05-03T16:43:00.0000000Z"}, {"name": "California Siblings Killed in Crash by Driver Who Was Allegedly Fleeing Police: 'Broke Our Hearts'", "url": "https://people.com/crime/california-siblings-killed-crash-driver-allegedly-fleeing-police/", "description": "The driver, identified as Robert Joseph Garcia, 18, of Morgan Hill, California, had allegedly changed lanes several times and made a U-turn without signaling on the Lawrenceville Expressway ...", "about": [{"readLink": "https://api.bing.microsoft.com/api/v7/entities/3009d91d-d582-4c34-85ba-772ba09e5be1", "name": "California"}, {"readLink": "https://api.bing.microsoft.com/api/v7/entities/49a4ec4f-908f-0c4c-0505-3c207533e598", "name": "Crash"}, {"readLink": "https://api.bing.microsoft.com/api/v7/entities/c0b725d2-befc-df93-915e-dd0fc857a1a6", "name": "People"}], "provider": [{"_type": "Organization", "name": "People"}], "datePublished": "2021-05-03T15:28:00.0000000Z"}]}