{"_type": "News", "readLink": "https://api.bing.microsoft.com/api/v7/news/search?q=%22Wendy+Jones%22%2binanchor%3apolice", "queryContext": {"originalQuery": "\"Wendy Jones\"+inanchor:police", "adultIntent": false}, "totalEstimatedMatches": 1, "sort": [{"name": "Best match", "id": "relevance", "isSelected": true, "url": "https://api.bing.microsoft.com/api/v7/news/search?q=%22Wendy+Jones%22%2binanchor%3apolice"}, {"name": "Most recent", "id": "date", "isSelected": false, "url": "https://api.bing.microsoft.com/api/v7/news/search?q=%22Wendy+Jones%22%2binanchor%3apolice&sortby=date"}], "value": [{"name": "Whatcom doctor says those choosing not to get vaccinated \u2018playing with fire\u2019", "url": "https://www.bellinghamherald.com/news/coronavirus/article251219454.html", "image": {"thumbnail": {"contentUrl": "https://www.bing.com/th?id=OVFT.x180fxrQ1k1dOtQcRegwti&pid=News", "width": 700, "height": 393}}, "description": "Almost 58% of Whatcom County residents who are eligible for vaccination (those 16 and older) have begun the process.", "about": [{"readLink": "https://api.bing.microsoft.com/api/v7/entities/2cf51dbc-e8d9-7a16-ed32-239c5b7747c0", "name": "Whatcom Community College"}], "mentions": [{"name": "Whatcom Community College"}, {"name": "Ko fight"}, {"name": "Certified first responder"}], "provider": [{"_type": "Organization", "name": "The Bellingham Herald", "image": {"thumbnail": {"contentUrl": "https://www.bing.com/th?id=AR_23700d9c0be5dae03ce9c3151e526761&pid=news"}}}], "datePublished": "2021-05-17T11:00:00.0000000Z", "video": {"name": "Whatcom doctor says those choosing not to get vaccinated \u2018playing with fire\u2019", "thumbnailUrl": "https://www.bing.com/th?id=OVF.hdcsH8z3fT%2FF7v3mPqNMpg&pid=News", "thumbnail": {"width": 300, "height": 168}}, "category": "World"}]}