{"_type": "News", "readLink": "https://api.bing.microsoft.com/api/v7/news/search?q=%22Joshua+Grubb%22%2binanchor%3apolice", "queryContext": {"originalQuery": "\"Joshua Grubb\"+inanchor:police", "adultIntent": false}, "totalEstimatedMatches": 1, "sort": [{"name": "Best match", "id": "relevance", "isSelected": true, "url": "https://api.bing.microsoft.com/api/v7/news/search?q=%22Joshua+Grubb%22%2binanchor%3apolice"}, {"name": "Most recent", "id": "date", "isSelected": false, "url": "https://api.bing.microsoft.com/api/v7/news/search?q=%22Joshua+Grubb%22%2binanchor%3apolice&sortby=date"}], "value": [{"name": "Williams jury indicts Defiance man for robbery", "url": "https://www.crescent-news.com/crimewatch/local_crime/williams-jury-indicts-defiance-man-for-robbery/article_a98ed3a7-5033-5ee0-b28e-c0003ba5e934.html", "description": "A Williams County grand jury has returned indictments against 25 persons, including one person for rape and a Defiance man for aggravated robbery, according to Prosecutor Katie Zartman\u2019s", "about": [{"readLink": "https://api.bing.microsoft.com/api/v7/entities/8e3e6d39-84b5-4e1c-a1af-559f21243f3e", "name": "Allen Williams"}, {"readLink": "https://api.bing.microsoft.com/api/v7/entities/9c6133e9-8291-619c-5626-ec4de47dcf3a", "name": "Crime"}], "provider": [{"_type": "Organization", "name": "The Crescent-News", "image": {"thumbnail": {"contentUrl": "https://www.bing.com/th?id=AR_0fdaf69a67511c46730705ea96327704&pid=news"}}}], "datePublished": "2021-05-29T05:00:00.0000000Z", "category": "US"}]}