{"_type": "News", "readLink": "https://api.bing.microsoft.com/api/v7/news/search?q=%22Herbert+Gilbert%22%2binanchor%3apolice", "queryContext": {"originalQuery": "\"Herbert Gilbert\"+inanchor:police", "adultIntent": false}, "totalEstimatedMatches": 2, "sort": [{"name": "Best match", "id": "relevance", "isSelected": true, "url": "https://api.bing.microsoft.com/api/v7/news/search?q=%22Herbert+Gilbert%22%2binanchor%3apolice"}, {"name": "Most recent", "id": "date", "isSelected": false, "url": "https://api.bing.microsoft.com/api/v7/news/search?q=%22Herbert+Gilbert%22%2binanchor%3apolice&sortby=date"}], "value": [{"name": "Carpe Diem dancers seize the day", "url": "https://www.madisonvillemeteor.com/index.php/news/carpe-diem-dancers-seize-day", "image": {"thumbnail": {"contentUrl": "https://www.bing.com/th?id=OVFT.cDRVprXTaGVTIwBCjuwbrC&pid=News", "width": 700, "height": 354}}, "description": "Carpe Diem Dance and Fitness studio\u2019s competitive team has brought home numerous awards to start their season in three regional competitions, including two in Houston, with two national competitions on the horizon,", "about": [{"readLink": "https://api.bing.microsoft.com/api/v7/entities/d7d0637f-a27f-390d-4456-e98ad5ceb393", "name": "Madisonville"}], "provider": [{"_type": "Organization", "name": "The Madisonville Meteor"}], "datePublished": "2021-05-19T13:41:00.0000000Z"}, {"name": "Update from the State Capitol", "url": "https://www.madisonvillemeteor.com/index.php/opinion/update-state-capitol-16", "image": {"thumbnail": {"contentUrl": "https://www.bing.com/th?id=OVFT.f-B1wWybHqP4rj5F7lY0oi&pid=News", "width": 528, "height": 550}}, "description": "A little over two weeks is all that\u2019s left of the 87th Legislative Session. Deadlines alluded to in previous columns have come and gone, and we are now in the final countdown. These deadlines, referred to as the \u201cSplit Session Amendments,", "about": [{"readLink": "https://api.bing.microsoft.com/api/v7/entities/404d337a-993a-a83f-1d2f-95908ffdafea", "name": "Madisonville"}], "provider": [{"_type": "Organization", "name": "The Madisonville Meteor"}], "datePublished": "2021-05-19T10:00:00.0000000Z"}]}