{"_type": "News", "readLink": "https://api.bing.microsoft.com/api/v7/news/search?q=%22Deon+Williams%22%2binanchor%3apolice", "queryContext": {"originalQuery": "\"Deon Williams\"+inanchor:police", "adultIntent": false}, "totalEstimatedMatches": 1, "sort": [{"name": "Best match", "id": "relevance", "isSelected": true, "url": "https://api.bing.microsoft.com/api/v7/news/search?q=%22Deon+Williams%22%2binanchor%3apolice"}, {"name": "Most recent", "id": "date", "isSelected": false, "url": "https://api.bing.microsoft.com/api/v7/news/search?q=%22Deon+Williams%22%2binanchor%3apolice&sortby=date"}], "value": [{"name": "Police: Dogs, cat rescued from back of stolen shipping van in East Huntingdon", "url": "https://triblive.com/local/westmoreland/dogs-cat-rescued-from-back-of-shipping-van-in-east-huintingdon/", "description": "Troopers learned the vehicle had been reported stolen in Tennessee and arrested the driver, Kaylon Deon Williams, 28, of Patterson N.J., according to court papers. Police found marijuana and ...", "provider": [{"_type": "Organization", "name": "TribLIVE.com"}], "datePublished": "2019-07-22T17:36:00.0000000Z"}]}